csv2tsv/__init__.py
csv2tsv/__main__.py
csv2tsv/to_tsv.py
csv2tsv-1.1.0.dist-info/LICENSE
csv2tsv-1.1.0.dist-info/METADATA
csv2tsv-1.1.0.dist-info/WHEEL
csv2tsv-1.1.0.dist-info/top_level.txt
csv2tsv-1.1.0.dist-info/RECORD
