Metadata-Version: 2.1
Name: csv2tsv
Version: 1.1.0
Summary: convert csv file to tsv file.
Home-page: https://github.com/not-dev/csv-to-tsv
License: MIT License
Platform: UNKNOWN
